README.rst
setup.py
src/flake8_import_graph/__init__.py
src/flake8_import_graph/checker.py
src/flake8_import_graph.egg-info/PKG-INFO
src/flake8_import_graph.egg-info/SOURCES.txt
src/flake8_import_graph.egg-info/dependency_links.txt
src/flake8_import_graph.egg-info/entry_points.txt
src/flake8_import_graph.egg-info/requires.txt
src/flake8_import_graph.egg-info/top_level.txt