Metadata-Version: 1.1
Name: flake8-import-graph
Version: 0.1.0
Summary: A flake8 lint to enforce that some modules can't be imported from other modules.
Home-page: http://github.com/tailhook/flake8-import-graph
Author: Paul Colomiets
Author-email: paul@colomiets.name
License: UNKNOWN
Platform: UNKNOWN
Classifier: Framework :: Flake8
Classifier: Environment :: Console
Classifier: Intended Audience :: Developers
Classifier: License :: OSI Approved :: MIT License
Classifier: Programming Language :: Python
Classifier: Programming Language :: Python :: 3
Classifier: Topic :: Software Development :: Libraries :: Python Modules
Classifier: Topic :: Software Development :: Quality Assurance
